[{"model": "clinic.periscopedatatype", "pk": 1, "fields": {"ugly_name": "patient-age", "pretty_name": "Age", "search_name": "Age", "output_prefix": "Age", "output_suffix": "", "patient_facing_label": "", "patient_facing_description": "", "clinician_facing_label": "", "clinician_facing_description": "", "html": "\n            <input type=\"number\" min=\"0\" max=\"125\" step=\"1\">\n        "}}, {"model": "clinic.periscopedatatype", "pk": 2, "fields": {"ugly_name": "patient-sex", "pretty_name": "Sex", "search_name": "Sex / Gender", "output_prefix": "Sex", "output_suffix": "", "patient_facing_label": "", "patient_facing_description": "", "clinician_facing_label": "", "clinician_facing_description": "", "html": "\n            <div class=\"selectbox\">\n                <select autocomplete=\"off\">\n                    <option selected value=\"\"></option>\n                    <option value=\"M\">Male</option>\n                    <option value=\"F\">Female</option>\n                </select>\n            </div>\n        "}}, {"model": "clinic.periscopedatatype", "pk": 3, "fields": {"ugly_name": "patient-height", "pretty_name": "Height (cm)", "search_name": "Height", "output_prefix": "Height", "output_suffix": "", "patient_facing_label": "", "patient_facing_description": "", "clinician_facing_label": "", "clinician_facing_description": "", "html": "\n            <input type=\"number\" step=\"0.1\" min=\"0\" max=\"300\">\n        "}}, {"model": "clinic.periscopedatatype", "pk": 4, "fields": {"ugly_name": "patient-weight", "pretty_name": "Weight (kg)", "search_name": "Weight", "output_prefix": "Weight", "output_suffix": "", "patient_facing_label": "", "patient_facing_description": "", "clinician_facing_label": "", "clinician_facing_description": "", "html": "\n            <input type=\"number\" step=\"0.1\" min=\"0\" max=\"400\">\n        "}}, {"model": "clinic.periscopedatatype", "pk": 5, "fields": {"ugly_name": "patient-bmi", "pretty_name": "BMI (auto)", "search_name": "BMI", "output_prefix": "BMI", "output_suffix": "", "patient_facing_label": "", "patient_facing_description": "", "clinician_facing_label": "", "clinician_facing_description": "", "html": "\n            <input type=\"text\" readonly tabindex=\"-1\">\n        "}}, {"model": "clinic.periscopedatatype", "pk": 6, "fields": {"ugly_name": "appointment-mode", "pretty_name": "Mode", "search_name": "Mode (telephone/face-to-face)", "output_prefix": "Appointment mode", "output_suffix": "", "patient_facing_label": "", "patient_facing_description": "", "clinician_facing_label": "", "clinician_facing_description": "", "html": "\n            <div class=\"selectbox\">\n                <select autocomplete=\"off\">\n                    <option value=\"\" selected></option>\n                    <option value=\"face-to-face\">Face-to-face</option>\n                    <option value=\"telephone\">Telephone</option>\n                </select>\n            </div>\n        "}}, {"model": "clinic.periscopedatatype", "pk": 7, "fields": {"ugly_name": "operation-freetext", "pretty_name": "Operation", "search_name": "Operation Name", "output_prefix": "Operation", "output_suffix": "", "patient_facing_label": "", "patient_facing_description": "", "clinician_facing_label": "", "clinician_facing_description": "", "html": "<input type=\"text\">"}}, {"model": "clinic.periscopedatatype", "pk": 8, "fields": {"ugly_name": "operation-risk", "pretty_name": "Risk", "search_name": "Operation Risk", "output_prefix": "Operation risk", "output_suffix": "", "patient_facing_label": "", "patient_facing_description": "", "clinician_facing_label": "", "clinician_facing_description": "", "html": "\n            <div class=\"selectbox\">\n                <select autocomplete=\"off\">\n                    <option value=\"\" selected></option>\n                    <option value=\"low\">Low</option>\n                    <option value=\"intermediate\">Intermediate</option>\n                    <option value=\"high\">High</option>\n                </select>\n            </div>\n        "}}, {"model": "clinic.periscopedatatype", "pk": 9, "fields": {"ugly_name": "patient-mets", "pretty_name": "METs", "search_name": "Metabolic Equivalents (METs)", "output_prefix": "METs", "output_suffix": "", "patient_facing_label": "", "patient_facing_description": "", "clinician_facing_label": "", "clinician_facing_description": "", "html": "\n            <div class=\"selectbox\">\n                <select autocomplete=\"off\">\n                    <option value=\"\" selected></option>\n                    <option value=\"LESS than 4\">&lt; 4</option>\n                    <option value=\"approximately 4\">~ 4</option>\n                    <option value=\"more than 4\">&gt; 4</option>\n                </select>\n            </div>\n        "}}, {"model": "clinic.periscopedatatype", "pk": 10, "fields": {"ugly_name": "patient-flat", "pretty_name": "Can Lie Flat", "search_name": "Can Lie Flat", "output_prefix": "Can lie flat", "output_suffix": "", "patient_facing_label": "", "patient_facing_description": "", "clinician_facing_label": "", "clinician_facing_description": "", "html": "\n            <div class=\"selectbox\">\n                <select autocomplete=\"off\">\n                    <option value=\"\" selected></option>\n                    <option value=\"Able to lay flat comfortably\">Yes</option>\n                    <option value=\"UNABLE to lay flat comfortably\">No</option>\n                </select>\n            </div>\n        "}}, {"model": "clinic.periscopedatatype", "pk": 11, "fields": {"ugly_name": "patient-mets-details", "pretty_name": "Exercise Tolerance", "search_name": "Exercise Tolerance", "output_prefix": "Exercise tolerance", "output_suffix": "", "patient_facing_label": "", "patient_facing_description": "", "clinician_facing_label": "", "clinician_facing_description": "", "html": "<input type=\"text\">"}}, {"model": "clinic.periscopedatatype", "pk": 12, "fields": {"ugly_name": "rockwood-cfs", "pretty_name": "Frailty Score", "search_name": "Rockwood Clinical Frailty Score", "output_prefix": "Rockwood CFS", "output_suffix": "", "patient_facing_label": "", "patient_facing_description": "", "clinician_facing_label": "", "clinician_facing_description": "", "html": "\n            <div class=\"selectbox\">\n                <select autocomplete=\"off\">\n                    <option value=\"\" selected></option>\n                    <option value=\"1 (very fit)\">1 – Very Fit</option>\n                    <option value=\"2 (well)\">2 – Well</option>\n                    <option value=\"3 (managing well)\">3 – Managing Well</option>\n                    <option value=\"4 (vulnerable)\">4 – Vulnerable</option>\n                    <option value=\"5 (mildly frail)\">5 – Mildly Frail</option>\n                    <option value=\"6 (moderately frail)\">6 – Moderately Frail</option>\n                    <option value=\"7 (severely frail)\">7 – Severely Frail</option>\n                    <option value=\"8 (very severely frail)\">8 – Very Severely Frail</option>\n                    <option value=\"9 (terminally ill)\">9 – Terminally Ill</option>\n                </select>\n            </div>\n        "}}, {"model": "clinic.periscopedatatype", "pk": 13, "fields": {"ugly_name": "smoking-status", "pretty_name": "Smoking", "search_name": "Smoking Status", "output_prefix": "Smoking status", "output_suffix": "", "patient_facing_label": "", "patient_facing_description": "", "clinician_facing_label": "", "clinician_facing_description": "", "html": "\n            <div class=\"selectbox\">\n                <select autocomplete=\"off\">\n                    <option value=\"\" selected></option>\n                    <option value=\"active smoker\">Active smoker</option>\n                    <option value=\"ex-smoker\">Ex-smoker</option>\n                    <option value=\"never smoked\">Never smoked</option>\n                </select>\n            </div>\n        "}}, {"model": "clinic.periscopedatatype", "pk": 14, "fields": {"ugly_name": "alcohol-freetext", "pretty_name": "Alcohol", "search_name": "Alcohol (etOH) Use", "output_prefix": "Alcohol", "output_suffix": "", "patient_facing_label": "", "patient_facing_description": "", "clinician_facing_label": "", "clinician_facing_description": "", "html": "<input type=\"text\">"}}, {"model": "clinic.periscopedatatype", "pk": 15, "fields": {"ugly_name": "drugs-freetext", "pretty_name": "Drugs", "search_name": "Substance Use (Drugs)", "output_prefix": "Drugs", "output_suffix": "", "patient_facing_label": "", "patient_facing_description": "", "clinician_facing_label": "", "clinician_facing_description": "", "html": "<input type=\"text\">"}}, {"model": "clinic.periscopedatatype", "pk": 16, "fields": {"ugly_name": "occupation-freetext", "pretty_name": "Occupation", "search_name": "Employment / Occupation", "output_prefix": "Occupation", "output_suffix": "", "patient_facing_label": "", "patient_facing_description": "", "clinician_facing_label": "", "clinician_facing_description": "", "html": "<input type=\"text\">"}}, {"model": "clinic.periscopedatatype", "pk": 17, "fields": {"ugly_name": "functioning-freetext", "pretty_name": "Functioning", "search_name": "Functioning and ADLs", "output_prefix": "Functioning", "output_suffix": "", "patient_facing_label": "", "patient_facing_description": "", "clinician_facing_label": "", "clinician_facing_description": "", "html": "<input type=\"text\">"}}, {"model": "clinic.periscopedatatype", "pk": 18, "fields": {"ugly_name": "medications-freetext", "pretty_name": "Current Medications", "search_name": "Current Medications (Rx)", "output_prefix": "Current medications", "output_suffix": "", "patient_facing_label": "", "patient_facing_description": "", "clinician_facing_label": "", "clinician_facing_description": "", "html": "<textarea autocomplete=\"off\" autocapitalize=\"off\" spellcheck=\"false\" placeholder=\"\"></textarea>"}}, {"model": "clinic.periscopedatatype", "pk": 19, "fields": {"ugly_name": "supplements-freetext", "pretty_name": "Supplements", "search_name": "Supplements", "output_prefix": "Supplements", "output_suffix": "", "patient_facing_label": "", "patient_facing_description": "", "clinician_facing_label": "", "clinician_facing_description": "", "html": "<textarea autocomplete=\"off\" autocapitalize=\"off\" spellcheck=\"false\" placeholder=\"\"></textarea>"}}, {"model": "clinic.periscopedatatype", "pk": 20, "fields": {"ugly_name": "allergies-freetext", "pretty_name": "Adverse Drug Reactions", "search_name": "Adverse Drug Reactions (Allergies)", "output_prefix": "Allergies", "output_suffix": "", "patient_facing_label": "", "patient_facing_description": "", "clinician_facing_label": "", "clinician_facing_description": "", "html": "<textarea autocomplete=\"off\" autocapitalize=\"off\" spellcheck=\"false\" placeholder=\"\"></textarea>"}}, {"model": "clinic.periscopedatatype", "pk": 21, "fields": {"ugly_name": "previous-anaesthesia-freetext", "pretty_name": "Previous Anaesthesia", "search_name": "Surgical and Anaesthetic History", "output_prefix": "Previous anaesthesia", "output_suffix": "", "patient_facing_label": "", "patient_facing_description": "", "clinician_facing_label": "", "clinician_facing_description": "", "html": "<textarea autocomplete=\"off\" autocapitalize=\"off\" spellcheck=\"false\" placeholder=\"\"></textarea>"}}, {"model": "clinic.periscopedatatype", "pk": 22, "fields": {"ugly_name": "previous-bvm", "pretty_name": "BVM", "search_name": "Bag Valve Mask (BVM)", "output_prefix": "BVM", "output_suffix": "", "patient_facing_label": "", "patient_facing_description": "", "clinician_facing_label": "", "clinician_facing_description": "", "html": "<input type=\"text\" placeholder=\"Difficulty, adjuncts\">"}}, {"model": "clinic.periscopedatatype", "pk": 23, "fields": {"ugly_name": "previous-lma", "pretty_name": "LMA", "search_name": "Laryngeal Mask Airway (LMA)", "output_prefix": "LMA", "output_suffix": "", "patient_facing_label": "", "patient_facing_description": "", "clinician_facing_label": "", "clinician_facing_description": "", "html": "<input type=\"text\" placeholder=\"Size, type\">"}}, {"model": "clinic.periscopedatatype", "pk": 24, "fields": {"ugly_name": "previous-ett", "pretty_name": "ETT", "search_name": "Endotracheal Intubation (ETT)", "output_prefix": "ETT", "output_suffix": "", "patient_facing_label": "", "patient_facing_description": "", "clinician_facing_label": "", "clinician_facing_description": "", "html": "<input type=\"text\" placeholder=\"Scope, view, BURP\">"}}, {"model": "clinic.periscopedatatype", "pk": 25, "fields": {"ugly_name": "previous-anaesthesia-complications", "pretty_name": "Complications", "search_name": "Complications from Anaesthesia", "output_prefix": "Complications", "output_suffix": "", "patient_facing_label": "", "patient_facing_description": "", "clinician_facing_label": "", "clinician_facing_description": "", "html": "<input type=\"text\">"}}, {"model": "clinic.periscopedatatype", "pk": 26, "fields": {"ugly_name": "previous-anaesthesia-fhx", "pretty_name": "Family Issues with Anaesthesia", "search_name": "Family History (FHx) of Issues with Anaesthesia", "output_prefix": "Complications", "output_suffix": "", "patient_facing_label": "", "patient_facing_description": "", "clinician_facing_label": "", "clinician_facing_description": "", "html": "\n            <div class=\"selectbox\">\n                <select autocomplete=\"off\">\n                    <option value=\"\" selected></option>\n                    <option value=\"Has a FHx of issues with anaesthesia\">Yes</option>\n                    <option value=\"No known FHx of issues with anaesthesia\">No</option>\n                </select>\n            </div>\n        "}}, {"model": "clinic.periscopedatatype", "pk": 27, "fields": {"ugly_name": "airway-dentition", "pretty_name": "Dentition", "search_name": "Dentition/Teeth Assessment", "output_prefix": "Dentition", "output_suffix": "", "patient_facing_label": "", "patient_facing_description": "", "clinician_facing_label": "", "clinician_facing_description": "", "html": "<input type=\"text\">"}}, {"model": "clinic.periscopedatatype", "pk": 28, "fields": {"ugly_name": "airway-mallampati", "pretty_name": "Mallampati", "search_name": "Mallampati Score", "output_prefix": "Mallampati", "output_suffix": "", "patient_facing_label": "", "patient_facing_description": "", "clinician_facing_label": "", "clinician_facing_description": "", "html": "\n            <div class=\"selectbox\">\n                <select autocomplete=\"off\">\n                    <option value=\"\" selected></option>\n                    <option value=\"1\">1</option>\n                    <option value=\"2\">2</option>\n                    <option value=\"3\">3</option>\n                    <option value=\"4\">4</option>\n                </select>\n            </div>\n        "}}, {"model": "clinic.periscopedatatype", "pk": 29, "fields": {"ugly_name": "airway-mouth-opening", "pretty_name": "Mouth Opening (cm)", "search_name": "Mouth Opening", "output_prefix": "Mouth opening", "output_suffix": "", "patient_facing_label": "", "patient_facing_description": "", "clinician_facing_label": "", "clinician_facing_description": "", "html": "<input type=\"number\" min=\"0\" max=\"7\" step=\"1\">"}}, {"model": "clinic.periscopedatatype", "pk": 30, "fields": {"ugly_name": "airway-tmd", "pretty_name": "TMD (cm)", "search_name": "Thyromental Distance", "output_prefix": "Thyromental distance", "output_suffix": "", "patient_facing_label": "", "patient_facing_description": "", "clinician_facing_label": "", "clinician_facing_description": "", "html": "<input type=\"number\" min=\"0\" max=\"12\" step=\"1\">"}}, {"model": "clinic.periscopedatatype", "pk": 31, "fields": {"ugly_name": "airway-cricothyroid", "pretty_name": "Cricothyroid", "search_name": "Cricothyroid Membrane", "output_prefix": "Cricothyroid membrane", "output_suffix": "", "patient_facing_label": "", "patient_facing_description": "", "clinician_facing_label": "", "clinician_facing_description": "", "html": "\n            <div class=\"selectbox\">\n                <select autocomplete=\"off\">\n                    <option value=\"\" selected></option>\n                    <option value=\"easily palpable\">Easily palpable</option>\n                    <option value=\"intermediate\">Intermediate</option>\n                    <option value=\"difficult\">Difficult to locate</option>\n                    <option value=\"IMPALPABLE\">Impalpable</option>\n                </select>\n            </div>\n        "}}, {"model": "clinic.periscopedatatype", "pk": 32, "fields": {"ugly_name": "airway-jaw-protrusion", "pretty_name": "Jaw Protrusion", "search_name": "Jaw Protrusion Class", "output_prefix": "Jaw protrusion", "output_suffix": "", "patient_facing_label": "", "patient_facing_description": "", "clinician_facing_label": "", "clinician_facing_description": "", "html": "\n            <div class=\"selectbox\">\n                <select autocomplete=\"off\">\n                    <option value=\"\" selected></option>\n                    <option value=\"A\">A</option>\n                    <option value=\"B\">B</option>No\n                    <option value=\"C\">C</option>\n                </select>\n            </div>\n        "}}, {"model": "clinic.periscopedatatype", "pk": 33, "fields": {"ugly_name": "airway-neckrom", "pretty_name": "Neck ROM", "search_name": "Neck Range of Motion (ROM)", "output_prefix": "Neck ROM", "output_suffix": "", "patient_facing_label": "", "patient_facing_description": "", "clinician_facing_label": "", "clinician_facing_description": "", "html": "\n            <div class=\"selectbox\">\n                <select autocomplete=\"off\">\n                    <option value=\"\" selected></option>\n                    <option value=\"normal\">Normal</option>\n                    <option value=\"mildly limited\">Mildly limited</option>\n                    <option value=\"moderately limited\">Moderately limited</option>\n                    <option value=\"severely limited\">Severely limited</option>\n                    <option value=\"immobile\">Immobile</option>\n                </select>\n            </div>\n        "}}, {"model": "clinic.periscopedatatype", "pk": 34, "fields": {"ugly_name": "airway-beard", "pretty_name": "Beard", "search_name": "Beard", "output_prefix": "Beard", "output_suffix": "", "patient_facing_label": "", "patient_facing_description": "", "clinician_facing_label": "", "clinician_facing_description": "", "html": "\n            <div class=\"selectbox\">\n                <select autocomplete=\"off\">\n                    <option value=\"\" selected></option>\n                    <option value=\"YES, will trim\">Will trim</option>\n                    <option value=\"YES, won't trim\">Won't trim</option>\n                    <option value=\"no\">No</option>\n                </select>\n            </div>\n        "}}, {"model": "clinic.periscopedatatype", "pk": 35, "fields": {"ugly_name": "vein-quality", "pretty_name": "Vein Quality", "search_name": "Vein Quality", "output_prefix": "Vein Quality", "output_suffix": "", "patient_facing_label": "", "patient_facing_description": "", "clinician_facing_label": "", "clinician_facing_description": "", "html": "\n            <div class=\"selectbox\">\n                <select autocomplete=\"off\">\n                    <option value=\"\" selected></option>\n                    <option value=\"good\">Good</option>\n                    <option value=\"fair\">Fair</option>\n                    <option value=\"poor\">Poor</option>\n                    <option value=\"very poor\">Very poor</option>\n                </select>\n            </div>\n        "}}, {"model": "clinic.periscopedatatype", "pk": 36, "fields": {"ugly_name": "examination-heart", "pretty_name": "Heart", "search_name": "Heart Sounds", "output_prefix": "Heart sounds", "output_suffix": "", "patient_facing_label": "", "patient_facing_description": "", "clinician_facing_label": "", "clinician_facing_description": "", "html": "<input type=\"text\">"}}, {"model": "clinic.periscopedatatype", "pk": 37, "fields": {"ugly_name": "examination-lungs", "pretty_name": "Lungs", "search_name": "Lung Sounds", "output_prefix": "Lung sounds", "output_suffix": "", "patient_facing_label": "", "patient_facing_description": "", "clinician_facing_label": "", "clinician_facing_description": "", "html": "<input type=\"text\">"}}, {"model": "clinic.periscopedatatype", "pk": 38, "fields": {"ugly_name": "examination-freetext", "pretty_name": "Other Findings", "search_name": "Other Examination Findings", "output_prefix": "Other examination findings", "output_suffix": "", "patient_facing_label": "", "patient_facing_description": "", "clinician_facing_label": "", "clinician_facing_description": "", "html": "<textarea autocomplete=\"off\" autocapitalize=\"off\" spellcheck=\"false\" placeholder=\"\"></textarea>"}}, {"model": "clinic.periscopedatatype", "pk": 39, "fields": {"ugly_name": "investigations-source", "pretty_name": "Source", "search_name": "Investigations Source", "output_prefix": "Source", "output_suffix": "", "patient_facing_label": "", "patient_facing_description": "", "clinician_facing_label": "", "clinician_facing_description": "", "html": "<input type=\"text\" placeholder=\"When and where were these tests done?\">"}}, {"model": "clinic.periscopedatatype", "pk": 40, "fields": {"ugly_name": "investigations-fbc", "pretty_name": "FBC", "search_name": "Full Blood Count (FBC)", "output_prefix": "FBC", "output_suffix": "", "patient_facing_label": "", "patient_facing_description": "", "clinician_facing_label": "", "clinician_facing_description": "", "html": "<input type=\"text\">"}}, {"model": "clinic.periscopedatatype", "pk": 41, "fields": {"ugly_name": "investigations-uec", "pretty_name": "UEC", "search_name": "Urea and Electrolytes (UEC)", "output_prefix": "UEC", "output_suffix": "", "patient_facing_label": "", "patient_facing_description": "", "clinician_facing_label": "", "clinician_facing_description": "", "html": "<input type=\"text\">"}}, {"model": "clinic.periscopedatatype", "pk": 42, "fields": {"ugly_name": "investigations-lft", "pretty_name": "LFT", "search_name": "Liver Function Tests (LFTs)", "output_prefix": "LFT", "output_suffix": "", "patient_facing_label": "", "patient_facing_description": "", "clinician_facing_label": "", "clinician_facing_description": "", "html": "<input type=\"text\">"}}, {"model": "clinic.periscopedatatype", "pk": 43, "fields": {"ugly_name": "investigations-hba1c", "pretty_name": "HbA1c", "search_name": "Glycosylated Haemoglobin (HbA1c)", "output_prefix": "HbA1c", "output_suffix": "", "patient_facing_label": "", "patient_facing_description": "", "clinician_facing_label": "", "clinician_facing_description": "", "html": "<input type=\"number\" min=\"4\" max=\"30\" step=\"0.1\">"}}, {"model": "clinic.periscopedatatype", "pk": 44, "fields": {"ugly_name": "investigations-haematinics", "pretty_name": "Iron Studies", "search_name": "Iron Studies (Haematinics)", "output_prefix": "Iron studies", "output_suffix": "", "patient_facing_label": "", "patient_facing_description": "", "clinician_facing_label": "", "clinician_facing_description": "", "html": "<input type=\"text\">"}}, {"model": "clinic.periscopedatatype", "pk": 45, "fields": {"ugly_name": "investigations-coags", "pretty_name": "Coags", "search_name": "Coagulation Profile", "output_prefix": "Coagulation profile", "output_suffix": "", "patient_facing_label": "", "patient_facing_description": "", "clinician_facing_label": "", "clinician_facing_description": "", "html": "<input type=\"text\">"}}, {"model": "clinic.periscopedatatype", "pk": 46, "fields": {"ugly_name": "investigations-ecg", "pretty_name": "ECG", "search_name": "Electrocardiogram (ECG)", "output_prefix": "ECG", "output_suffix": "", "patient_facing_label": "", "patient_facing_description": "", "clinician_facing_label": "", "clinician_facing_description": "", "html": "<input type=\"text\">"}}, {"model": "clinic.periscopedatatype", "pk": 47, "fields": {"ugly_name": "investigations-other", "pretty_name": "Other Investigations", "search_name": "Other Investigations", "output_prefix": "Other investigations", "output_suffix": "", "patient_facing_label": "", "patient_facing_description": "", "clinician_facing_label": "", "clinician_facing_description": "", "html": "<textarea autocomplete=\"off\" autocapitalize=\"off\" spellcheck=\"false\" placeholder=\"\"></textarea>"}}, {"model": "clinic.periscopedatatype", "pk": 48, "fields": {"ugly_name": "consent-source", "pretty_name": "Consent Source", "search_name": "Consent Source", "output_prefix": "Consent Source", "output_suffix": "", "patient_facing_label": "", "patient_facing_description": "", "clinician_facing_label": "", "clinician_facing_description": "", "html": "\n            <div class=\"selectbox\">\n                <select autocomplete=\"off\">\n                    <option value=\"\" selected></option>\n                    <option value=\"patient\">Patient</option>\n                    <option value=\"next of kin\">Next of Kin</option>\n                    <option value=\"enduring guardian\">Enduring Guardian</option>\n                    <option value=\"state-appointed (public) guardian\">State-Appointed Guardian</option>\n                </select>\n            </div>\n        "}}, {"model": "clinic.periscopedatatype", "pk": 49, "fields": {"ugly_name": "consent-notes", "pretty_name": "Special Notes", "search_name": "Special Notes on Consent", "output_prefix": "Special notes", "output_suffix": "", "patient_facing_label": "", "patient_facing_description": "", "clinician_facing_label": "", "clinician_facing_description": "", "html": "<textarea autocomplete=\"off\" autocapitalize=\"off\" spellcheck=\"false\" placeholder=\"\"></textarea>"}}, {"model": "clinic.periscopedatatype", "pk": 50, "fields": {"ugly_name": "rcri-risky", "pretty_name": "Elevated Risk*", "search_name": "Elevated Risk", "output_prefix": "Elevated Risk", "output_suffix": "", "patient_facing_label": "", "patient_facing_description": "", "clinician_facing_label": "", "clinician_facing_description": "", "html": "<input type=\"checkbox\" tabindex=0>"}}, {"model": "clinic.periscopedatatype", "pk": 51, "fields": {"ugly_name": "rcri-ihd", "pretty_name": "IHD", "search_name": "IHD", "output_prefix": "IHD", "output_suffix": "", "patient_facing_label": "", "patient_facing_description": "", "clinician_facing_label": "", "clinician_facing_description": "", "html": "<input type=\"checkbox\" tabindex=0>"}}, {"model": "clinic.periscopedatatype", "pk": 52, "fields": {"ugly_name": "rcri-ccf", "pretty_name": "CCF", "search_name": "CCF", "output_prefix": "CCF", "output_suffix": "", "patient_facing_label": "", "patient_facing_description": "", "clinician_facing_label": "", "clinician_facing_description": "", "html": "<input type=\"checkbox\" tabindex=0>"}}, {"model": "clinic.periscopedatatype", "pk": 53, "fields": {"ugly_name": "rcri-cva", "pretty_name": "CVA", "search_name": "CVA", "output_prefix": "CVA", "output_suffix": "", "patient_facing_label": "", "patient_facing_description": "", "clinician_facing_label": "", "clinician_facing_description": "", "html": "<input type=\"checkbox\" tabindex=0>"}}, {"model": "clinic.periscopedatatype", "pk": 54, "fields": {"ugly_name": "rcri-insulin", "pretty_name": "In insulin", "search_name": "In insulin", "output_prefix": "In insulin", "output_suffix": "", "patient_facing_label": "", "patient_facing_description": "", "clinician_facing_label": "", "clinician_facing_description": "", "html": "<input type=\"checkbox\" tabindex=0>"}}, {"model": "clinic.periscopedatatype", "pk": 55, "fields": {"ugly_name": "rcri-creatinine", "pretty_name": "Cr > 176.8 μmol/L", "search_name": "Cr > 176.8 μmol/L", "output_prefix": "Cr > 176.8 μmol/L", "output_suffix": "", "patient_facing_label": "", "patient_facing_description": "", "clinician_facing_label": "", "clinician_facing_description": "", "html": "<input type=\"checkbox\" tabindex=0>"}}, {"model": "clinic.periscopedatatype", "pk": 56, "fields": {"ugly_name": "apfel-sex", "pretty_name": "Female", "search_name": "Female", "output_prefix": "Female", "output_suffix": "", "patient_facing_label": "", "patient_facing_description": "", "clinician_facing_label": "", "clinician_facing_description": "", "html": "<input type=\"checkbox\" tabindex=0>"}}, {"model": "clinic.periscopedatatype", "pk": 57, "fields": {"ugly_name": "apfel-smoking", "pretty_name": "Non-smoker", "search_name": "Non-smoker", "output_prefix": "Non-smoker", "output_suffix": "", "patient_facing_label": "", "patient_facing_description": "", "clinician_facing_label": "", "clinician_facing_description": "", "html": "<input type=\"checkbox\" tabindex=0>"}}, {"model": "clinic.periscopedatatype", "pk": 58, "fields": {"ugly_name": "apfel-ponv", "pretty_name": "Prior PONV", "search_name": "Prior PONV", "output_prefix": "Prior PONV", "output_suffix": "", "patient_facing_label": "", "patient_facing_description": "", "clinician_facing_label": "", "clinician_facing_description": "", "html": "<input type=\"checkbox\" tabindex=0>"}}, {"model": "clinic.periscopedatatype", "pk": 59, "fields": {"ugly_name": "apfel-opioids", "pretty_name": "Postop opioids", "search_name": "Postop opioids", "output_prefix": "Postop opioids", "output_suffix": "", "patient_facing_label": "", "patient_facing_description": "", "clinician_facing_label": "", "clinician_facing_description": "", "html": "<input type=\"checkbox\" tabindex=0>"}}, {"model": "clinic.periscopedatatype", "pk": 60, "fields": {"ugly_name": "patient-asa", "pretty_name": "ASA", "search_name": "ASA Physical Status Score", "output_prefix": "ASA", "output_suffix": "", "patient_facing_label": "", "patient_facing_description": "", "clinician_facing_label": "", "clinician_facing_description": "", "html": "\n            <div class=\"selectbox\">\n                <select autocomplete=\"off\">\n                    <option value=\"\" selected></option>\n                    <option value=\"1\">1</option>\n                    <option value=\"2\">2</option>\n                    <option value=\"3\">3</option>\n                    <option value=\"4\">4</option>\n                    <option value=\"5\">5</option>\n                    <option value=\"6\">6</option>\n                </select>\n            </div>\n        "}}, {"model": "clinic.periscopedatatype", "pk": 61, "fields": {"ugly_name": "sort-urgency", "pretty_name": "Urgency", "search_name": "Urgency (SORT)ge", "output_prefix": "Urgency", "output_suffix": "", "patient_facing_label": "", "patient_facing_description": "", "clinician_facing_label": "", "clinician_facing_description": "", "html": "\n            <div class=\"selectbox\">\n                <select autocomplete=\"off\">\n                    <option value=\"Elective\" selected>Elective</option>\n                    <option value=\"Expedited\">Expedited</option>\n                    <option value=\"Urgent\">Urgent</option>\n                    <option value=\"Immediate\">Immediate</option>\n                </select>\n            </div>\n        "}}, {"model": "clinic.periscopedatatype", "pk": 62, "fields": {"ugly_name": "sort-malignancy", "pretty_name": "Malignancy", "search_name": "Known Malignancy (SORT)", "output_prefix": "Malignancy", "output_suffix": "", "patient_facing_label": "", "patient_facing_description": "", "clinician_facing_label": "", "clinician_facing_description": "", "html": "\n            <div class=\"selectbox\">\n                <select autocomplete=\"off\">\n                    <option value=\"\" selected></option>\n                    <option value=\"Yes\">Yes</option>\n                    <option value=\"No\">No</option>\n                </select>\n            </div>\n        "}}, {"model": "clinic.periscopedatatype", "pk": 63, "fields": {"ugly_name": "sort-tgv", "pretty_name": "Thoracics, GI, or vascular?", "search_name": "Thoracics, GI, or Vascular (SORT)", "output_prefix": "Thoracics, GI, or vascular", "output_suffix": "", "patient_facing_label": "", "patient_facing_description": "", "clinician_facing_label": "", "clinician_facing_description": "", "html": "\n            <div class=\"selectbox\">\n                <select autocomplete=\"off\">\n                    <option value=\"\" selected></option>\n                    <option value=\"Yes\">Yes</option>\n                    <option value=\"No\">No</option>\n                </select>\n            </div>\n        "}}, {"model": "clinic.periscopedatatype", "pk": 64, "fields": {"ugly_name": "issues", "pretty_name": "Key Issues", "search_name": "Key Issues", "output_prefix": "Key Issues", "output_suffix": "", "patient_facing_label": "", "patient_facing_description": "", "clinician_facing_label": "", "clinician_facing_description": "", "html": "<textarea autocomplete=\"off\" autocapitalize=\"off\" spellcheck=\"false\" placeholder=\"\"></textarea>"}}, {"model": "clinic.periscopedatatype", "pk": 65, "fields": {"ugly_name": "plan", "pretty_name": "Anaesthetic Plan", "search_name": "Anaesthetic Plan", "output_prefix": "Anaesthetic Plan", "output_suffix": "", "patient_facing_label": "", "patient_facing_description": "", "clinician_facing_label": "", "clinician_facing_description": "", "html": "<textarea autocomplete=\"off\" autocapitalize=\"off\" spellcheck=\"false\" placeholder=\"\"></textarea>"}}, {"model": "clinic.periscopedatatype", "pk": 66, "fields": {"ugly_name": "plan-medications", "pretty_name": "Medications and Fasting", "search_name": "Medications and Fasting", "output_prefix": "Medications and Fasting", "output_suffix": "", "patient_facing_label": "", "patient_facing_description": "", "clinician_facing_label": "", "clinician_facing_description": "", "html": "<textarea autocomplete=\"off\" autocapitalize=\"off\" spellcheck=\"false\" placeholder=\"\"></textarea>"}}, {"model": "clinic.periscopedatatype", "pk": 67, "fields": {"ugly_name": "antiplatelet-use", "pretty_name": "Antiplatelets", "search_name": "", "output_prefix": "", "output_suffix": "", "patient_facing_label": "", "patient_facing_description": "", "clinician_facing_label": "", "clinician_facing_description": "", "html": "<div class=\"selectbox\">\n                <select autocomplete=\"off\">\n                    <option value=\"\" selected></option>\n                    <option value=\"single\">Single</option>\n                    <option value=\"dual\">Dual</option>\n                    <option value=\"none\">None</option>\n                </select>\n            </div>"}}, {"model": "clinic.periscopedatatype", "pk": 68, "fields": {"ugly_name": "smoking-details", "pretty_name": "Smoking Details", "search_name": "", "output_prefix": "", "output_suffix": "", "patient_facing_label": "", "patient_facing_description": "", "clinician_facing_label": "", "clinician_facing_description": "", "html": "<input type=\"text\" placeholder=\"Details\">"}}, {"model": "clinic.periscopedatatype", "pk": 69, "fields": {"ugly_name": "other-shx", "pretty_name": "Other", "search_name": "", "output_prefix": "", "output_suffix": "", "patient_facing_label": "", "patient_facing_description": "", "clinician_facing_label": "", "clinician_facing_description": "", "html": "<textarea autocomplete=\"off\" autocapitalize=\"off\" spellcheck=\"false\" placeholder=\"\"></textarea>"}}, {"model": "clinic.periscopedatatype", "pk": 70, "fields": {"ugly_name": "previous-anaesthesia-fhx-details", "pretty_name": "Details of Family Issues with Anaesthesia", "search_name": "", "output_prefix": "", "output_suffix": "", "patient_facing_label": "", "patient_facing_description": "", "clinician_facing_label": "", "clinician_facing_description": "", "html": "<input type=\"text\" placeholder=\"Details\">"}}, {"model": "clinic.periscopedatatype", "pk": 71, "fields": {"ugly_name": "consent-ga", "pretty_name": "General Anaesthesia", "search_name": "", "output_prefix": "", "output_suffix": "", "patient_facing_label": "", "patient_facing_description": "", "clinician_facing_label": "", "clinician_facing_description": "", "html": "<input type=\"checkbox\" tabindex=0>"}}, {"model": "clinic.periscopedatatype", "pk": 72, "fields": {"ugly_name": "consent-sedation", "pretty_name": "Sedation", "search_name": "", "output_prefix": "", "output_suffix": "", "patient_facing_label": "", "patient_facing_description": "", "clinician_facing_label": "", "clinician_facing_description": "", "html": "<input type=\"checkbox\" tabindex=0>"}}, {"model": "clinic.periscopedatatype", "pk": 73, "fields": {"ugly_name": "consent-regional", "pretty_name": "Regional", "search_name": "", "output_prefix": "", "output_suffix": "", "patient_facing_label": "", "patient_facing_description": "", "clinician_facing_label": "", "clinician_facing_description": "", "html": "<input type=\"checkbox\" tabindex=0>"}}, {"model": "clinic.periscopedatatype", "pk": 74, "fields": {"ugly_name": "consent-neuraxial", "pretty_name": "Neuraxial", "search_name": "", "output_prefix": "", "output_suffix": "", "patient_facing_label": "", "patient_facing_description": "", "clinician_facing_label": "", "clinician_facing_description": "", "html": "<input type=\"checkbox\" tabindex=0>"}}, {"model": "clinic.periscopedatatype", "pk": 75, "fields": {"ugly_name": "consent-artline", "pretty_name": "Arterial Line", "search_name": "", "output_prefix": "", "output_suffix": "", "patient_facing_label": "", "patient_facing_description": "", "clinician_facing_label": "", "clinician_facing_description": "", "html": "<input type=\"checkbox\" tabindex=0>"}}, {"model": "clinic.periscopedatatype", "pk": 76, "fields": {"ugly_name": "consent-cvc", "pretty_name": "Central Venous Access", "search_name": "", "output_prefix": "", "output_suffix": "", "patient_facing_label": "", "patient_facing_description": "", "clinician_facing_label": "", "clinician_facing_description": "", "html": "<input type=\"checkbox\" tabindex=0>"}}, {"model": "clinic.periscopedatatype", "pk": 77, "fields": {"ugly_name": "consent-blood", "pretty_name": "Blood Products", "search_name": "", "output_prefix": "", "output_suffix": "", "patient_facing_label": "", "patient_facing_description": "", "clinician_facing_label": "", "clinician_facing_description": "", "html": "<input type=\"checkbox\" tabindex=0>"}}, {"model": "clinic.periscopedatatype", "pk": 78, "fields": {"ugly_name": "stopbang-snorer", "pretty_name": "Snorer", "search_name": "", "output_prefix": "", "output_suffix": "", "patient_facing_label": "", "patient_facing_description": "", "clinician_facing_label": "", "clinician_facing_description": "", "html": "<input type=\"checkbox\" tabindex=0>"}}, {"model": "clinic.periscopedatatype", "pk": 79, "fields": {"ugly_name": "stopbang-tiredness", "pretty_name": "Tiredness", "search_name": "", "output_prefix": "", "output_suffix": "", "patient_facing_label": "", "patient_facing_description": "", "clinician_facing_label": "", "clinician_facing_description": "", "html": "<input type=\"checkbox\" tabindex=0>"}}, {"model": "clinic.periscopedatatype", "pk": 80, "fields": {"ugly_name": "stopbang-apnoea", "pretty_name": "Observed Apnoea", "search_name": "", "output_prefix": "", "output_suffix": "", "patient_facing_label": "", "patient_facing_description": "", "clinician_facing_label": "", "clinician_facing_description": "", "html": "<input type=\"checkbox\" tabindex=0>"}}, {"model": "clinic.periscopedatatype", "pk": 81, "fields": {"ugly_name": "stopbang-hypertensive", "pretty_name": "Hypertensive", "search_name": "", "output_prefix": "", "output_suffix": "", "patient_facing_label": "", "patient_facing_description": "", "clinician_facing_label": "", "clinician_facing_description": "", "html": "<input type=\"checkbox\" tabindex=0>"}}, {"model": "clinic.periscopedatatype", "pk": 82, "fields": {"ugly_name": "stopbang-bmi-35", "pretty_name": "BMI > 35", "search_name": "", "output_prefix": "", "output_suffix": "", "patient_facing_label": "", "patient_facing_description": "", "clinician_facing_label": "", "clinician_facing_description": "", "html": "<input type=\"checkbox\" tabindex=0>"}}, {"model": "clinic.periscopedatatype", "pk": 83, "fields": {"ugly_name": "stopbang-age", "pretty_name": "Age > 50", "search_name": "", "output_prefix": "", "output_suffix": "", "patient_facing_label": "", "patient_facing_description": "", "clinician_facing_label": "", "clinician_facing_description": "", "html": "<input type=\"checkbox\" tabindex=0>"}}, {"model": "clinic.periscopedatatype", "pk": 84, "fields": {"ugly_name": "stopbang-neck", "pretty_name": "Neck Circumference ≥ 40cm", "search_name": "", "output_prefix": "", "output_suffix": "", "patient_facing_label": "", "patient_facing_description": "", "clinician_facing_label": "", "clinician_facing_description": "", "html": "<input type=\"checkbox\" tabindex=0>"}}, {"model": "clinic.periscopedatatype", "pk": 85, "fields": {"ugly_name": "stopbang-male", "pretty_name": "Male", "search_name": "", "output_prefix": "", "output_suffix": "", "patient_facing_label": "", "patient_facing_description": "", "clinician_facing_label": "", "clinician_facing_description": "", "html": "<input type=\"checkbox\" tabindex=0>"}}, {"model": "clinic.periscopedatatype", "pk": 86, "fields": {"ugly_name": "rcri-score", "pretty_name": "RCRI Score", "search_name": "", "output_prefix": "", "output_suffix": "", "patient_facing_label": "", "patient_facing_description": "", "clinician_facing_label": "", "clinician_facing_description": "", "html": "<span></span>"}}, {"model": "clinic.periscopedatatype", "pk": 87, "fields": {"ugly_name": "apfel-score", "pretty_name": "Apfel Score", "search_name": "", "output_prefix": "", "output_suffix": "", "patient_facing_label": "", "patient_facing_description": "", "clinician_facing_label": "", "clinician_facing_description": "", "html": "<span></span>"}}, {"model": "clinic.periscopedatatype", "pk": 88, "fields": {"ugly_name": "sort-score", "pretty_name": "SORT Score", "search_name": "", "output_prefix": "", "output_suffix": "", "patient_facing_label": "", "patient_facing_description": "", "clinician_facing_label": "", "clinician_facing_description": "", "html": "<span></span>"}}, {"model": "clinic.periscopedatatype", "pk": 89, "fields": {"ugly_name": "cataract-already-done", "pretty_name": "Previous Cataract", "search_name": "", "output_prefix": "", "output_suffix": "", "patient_facing_label": "", "patient_facing_description": "", "clinician_facing_label": "", "clinician_facing_description": "", "html": "<input type=\"checkbox\" tabindex=0>"}}, {"model": "clinic.periscopedatatype", "pk": 90, "fields": {"ugly_name": "patient-language-barrier", "pretty_name": "Language Barrier", "search_name": "", "output_prefix": "", "output_suffix": "", "patient_facing_label": "", "patient_facing_description": "", "clinician_facing_label": "", "clinician_facing_description": "", "html": "<input type=\"checkbox\" tabindex=0>"}}, {"model": "clinic.periscopedatatype", "pk": 91, "fields": {"ugly_name": "patient-deaf", "pretty_name": "Hard of Hearing", "search_name": "", "output_prefix": "", "output_suffix": "", "patient_facing_label": "", "patient_facing_description": "", "clinician_facing_label": "", "clinician_facing_description": "", "html": "<input type=\"checkbox\" tabindex=0>"}}, {"model": "clinic.periscopedatatype", "pk": 92, "fields": {"ugly_name": "patient-ppmicd", "pretty_name": "Has a Pacemaker or ICD", "search_name": "", "output_prefix": "", "output_suffix": "", "patient_facing_label": "", "patient_facing_description": "", "clinician_facing_label": "", "clinician_facing_description": "", "html": "<input type=\"checkbox\" tabindex=0>"}}, {"model": "clinic.periscopedatatype", "pk": 93, "fields": {"ugly_name": "patient-unable-to-communicate", "pretty_name": "Unable to Communicate", "search_name": "", "output_prefix": "", "output_suffix": "", "patient_facing_label": "", "patient_facing_description": "", "clinician_facing_label": "", "clinician_facing_description": "", "html": "<input type=\"checkbox\" tabindex=0>"}}, {"model": "clinic.periscopedatatype", "pk": 94, "fields": {"ugly_name": "patient-cognitive-impairment", "pretty_name": "Cognitive Impairment", "search_name": "", "output_prefix": "", "output_suffix": "", "patient_facing_label": "", "patient_facing_description": "", "clinician_facing_label": "", "clinician_facing_description": "", "html": "<input type=\"checkbox\" tabindex=0>"}}, {"model": "clinic.periscopedatatype", "pk": 95, "fields": {"ugly_name": "patient-known-difficult-airway", "pretty_name": "Known Difficult Airway", "search_name": "", "output_prefix": "", "output_suffix": "", "patient_facing_label": "", "patient_facing_description": "", "clinician_facing_label": "", "clinician_facing_description": "", "html": "<input type=\"checkbox\" tabindex=0>"}}, {"model": "clinic.periscopedatatype", "pk": 96, "fields": {"ugly_name": "patient-known-mh", "pretty_name": "FHx Malignant Hyperthermia", "search_name": "", "output_prefix": "", "output_suffix": "", "patient_facing_label": "", "patient_facing_description": "", "clinician_facing_label": "", "clinician_facing_description": "", "html": "<input type=\"checkbox\" tabindex=0>"}}, {"model": "clinic.periscopedatatype", "pk": 97, "fields": {"ugly_name": "patient-recent-respiratory-illness", "pretty_name": "Recent Respiratory Illness", "search_name": "", "output_prefix": "", "output_suffix": "", "patient_facing_label": "", "patient_facing_description": "", "clinician_facing_label": "", "clinician_facing_description": "", "html": "<input type=\"checkbox\" tabindex=0>"}}, {"model": "clinic.periscopedatatype", "pk": 98, "fields": {"ugly_name": "patient-recent-cardiac-event", "pretty_name": "Recent Cardiac Event", "search_name": "", "output_prefix": "", "output_suffix": "", "patient_facing_label": "", "patient_facing_description": "", "clinician_facing_label": "", "clinician_facing_description": "", "html": "<input type=\"checkbox\" tabindex=0>"}}, {"model": "clinic.periscopedatatype", "pk": 99, "fields": {"ugly_name": "patient-recent-pe", "pretty_name": "Recent PE", "search_name": "", "output_prefix": "", "output_suffix": "", "patient_facing_label": "", "patient_facing_description": "", "clinician_facing_label": "", "clinician_facing_description": "", "html": "<input type=\"checkbox\" tabindex=0>"}}, {"model": "clinic.periscopedatatype", "pk": 100, "fields": {"ugly_name": "patient-recent-stroke", "pretty_name": "Recent Stroke", "search_name": "", "output_prefix": "", "output_suffix": "", "patient_facing_label": "", "patient_facing_description": "", "clinician_facing_label": "", "clinician_facing_description": "", "html": "<input type=\"checkbox\" tabindex=0>"}}, {"model": "clinic.periscopedatatype", "pk": 101, "fields": {"ugly_name": "patient-public-guardian", "pretty_name": "Public Guardian", "search_name": "", "output_prefix": "", "output_suffix": "", "patient_facing_label": "", "patient_facing_description": "", "clinician_facing_label": "", "clinician_facing_description": "", "html": "<input type=\"checkbox\" tabindex=0>"}}, {"model": "clinic.periscopedatatype", "pk": 102, "fields": {"ugly_name": "patient-cataract-lay-flat", "pretty_name": "Unable to Lay Flat", "search_name": "", "output_prefix": "", "output_suffix": "", "patient_facing_label": "", "patient_facing_description": "", "clinician_facing_label": "", "clinician_facing_description": "", "html": "<input type=\"checkbox\" tabindex=0>"}}, {"model": "clinic.periscopedatatype", "pk": 103, "fields": {"ugly_name": "hf-nyha", "pretty_name": "NYHA", "search_name": "NYHA", "output_prefix": "", "output_suffix": "", "patient_facing_label": "", "patient_facing_description": "", "clinician_facing_label": "", "clinician_facing_description": "", "html": "<div class=\"selectbox\">\n                <select autocomplete=\"off\">\n                    <option value=\"\" selected></option>\n                    <option value=\"1\">1</option>\n                    <option value=\"2\">2</option>\n                    <option value=\"3\">3</option>\n                    <option value=\"4\">4</option>\n                </select>\n            </div>"}}, {"model": "clinic.periscopedatatype", "pk": 104, "fields": {"ugly_name": "hf-lvef", "pretty_name": "LVEF", "search_name": "LVEF", "output_prefix": "", "output_suffix": "", "patient_facing_label": "", "patient_facing_description": "", "clinician_facing_label": "", "clinician_facing_description": "", "html": "<input type=\"number\" min=\"0\" max=\"100\" step=\"1\">"}}, {"model": "clinic.periscopedatatype", "pk": 105, "fields": {"ugly_name": "history-freetext", "pretty_name": "Other PMHx", "search_name": "", "output_prefix": "", "output_suffix": "", "patient_facing_label": "", "patient_facing_description": "", "clinician_facing_label": "", "clinician_facing_description": "", "html": "<textarea autocomplete=\"off\" autocapitalize=\"off\" spellcheck=\"false\" placeholder=\"\"></textarea>"}}]